oidckit/__init__.py
oidckit/crypto.py
oidckit/excs.py
oidckit/objects.py
oidckit/provider.py
oidckit/routines.py
oidckit-0.1.dist-info/LICENSE
oidckit-0.1.dist-info/METADATA
oidckit-0.1.dist-info/WHEEL
oidckit-0.1.dist-info/top_level.txt
oidckit-0.1.dist-info/RECORD
